LICENSE
README.md
setup.py
libsw3/__init__.py
libsw3/database.py
libsw3/libswn.py
libsw3/msgc.py
libsw3/qiwei.py
libsw3/recvmail.py
libsw3/sendemail.py
libsw3/sw.py
libsw3/utils.py
libsw3/workday.py
libsw3.egg-info/PKG-INFO
libsw3.egg-info/SOURCES.txt
libsw3.egg-info/dependency_links.txt
libsw3.egg-info/entry_points.txt
libsw3.egg-info/top_level.txt