Metadata-Version: 2.1
Name: libsw3
Version: 0.3.5
Summary: libsw3
Home-page: https://svn2.rtfund.com/svn/libsw3
Author: Chen chuan
Author-email: kcchen@139.com
Classifier: Programming Language :: Python :: 3
Classifier: License :: OSI Approved :: MIT License
Classifier: Operating System :: OS Independent
Requires-Python: >=3.5
License-File: LICENSE
